attrdictionary/__init__.py
attrdictionary/default.py
attrdictionary/dictionary.py
attrdictionary/mapping.py
attrdictionary/merge.py
attrdictionary/mixins.py
attrdictionary2-2.1.0.dist-info/LICENSE.txt
attrdictionary2-2.1.0.dist-info/METADATA
attrdictionary2-2.1.0.dist-info/WHEEL
attrdictionary2-2.1.0.dist-info/RECORD
