Metadata-Version: 2.1
Name: attrdictionary2
Version: 2.1.0
Summary: Fork of kiselas/AttrDictionary , itself a fork of bcj/AttrDict
Home-page: https://github.com/tigerhawkvok/AttrDictionary
License: MIT
Author: Philip Kahn
Author-email: tigerhawkvok@gmail.com
Requires-Python: >=3.7,<3.12
Classifier: License :: OSI Approved :: MIT License
Classifier: Programming Language :: Python :: 3
Classifier: Programming Language :: Python :: 3.7
Classifier: Programming Language :: Python :: 3.8
Classifier: Programming Language :: Python :: 3.9
Classifier: Programming Language :: Python :: 3.10
Classifier: Programming Language :: Python :: 3.11
Project-URL: Repository, https://github.com/tigerhawkvok/AttrDictionary
